Metadata-Version: 2.1
Name: pydantic-webargs
Version: 1.1.0
Summary: Pydatic webargs
Home-page: https://nf1s.github.io/pydantic-webargs/
Author: Ahmed Nafies
Author-email: ahmed.nafies@gmail.com
License: MIT
Project-URL: Documentation, https://nf1s.github.io/pydantic-webargs/
Project-URL: Source, https://github.com/nf1s/pydantic-webargs
Platform: UNKNOWN
Classifier: Intended Audience :: Developers
Classifier: Topic :: Utilities
Classifier: License :: OSI Approved :: MIT License
Classifier: Programming Language :: Python :: 3
Classifier: Programming Language :: Python :: 3.7
Classifier: Programming Language :: Python :: 3.8
Requires-Python: >=3.7
Provides-Extra: dev
Provides-Extra: docs
License-File: LICENSE.txt
